flask_gdrive/__init__.py
flask_gdrive/example.py
flask_gdrive/flask_gdrive.py
Flask_GDrive-1.0.dist-info/LICENSE
Flask_GDrive-1.0.dist-info/METADATA
Flask_GDrive-1.0.dist-info/WHEEL
Flask_GDrive-1.0.dist-info/top_level.txt
Flask_GDrive-1.0.dist-info/RECORD
